ecomp/__init__.py
ecomp/_version.py
ecomp/cli.py
ecomp/config.py
ecomp/io.py
ecomp/storage.py
ecomp/compression/__init__.py
ecomp/compression/consensus.py
ecomp/compression/encoding.py
ecomp/compression/pipeline.py
ecomp/compression/rle.py
ecomp/diagnostics/__init__.py
ecomp/diagnostics/checksums.py
ecomp/diagnostics/metrics.py
evolutionary_compression-0.0.1.dist-info/licenses/LICENSE
evolutionary_compression-0.0.1.dist-info/METADATA
evolutionary_compression-0.0.1.dist-info/WHEEL
evolutionary_compression-0.0.1.dist-info/entry_points.txt
evolutionary_compression-0.0.1.dist-info/top_level.txt
evolutionary_compression-0.0.1.dist-info/RECORD
