Metadata-Version: 2.4
Name: evolutionary-compression
Version: 0.0.1
Summary: Lossless evolutionary-aware multiple sequence alignment compressor
Author: Evolutionary Compression Team
License: MIT License
Project-URL: Documentation, https://example.com/docs
Project-URL: Repository, https://example.com/repo
Classifier: Programming Language :: Python :: 3
Classifier: Programming Language :: Python :: 3.11
Classifier: Programming Language :: Python :: 3.12
Classifier: License :: OSI Approved :: MIT License
Classifier: Operating System :: OS Independent
Requires-Python: >=3.11
License-File: LICENSE
Requires-Dist: biopython>=1.83
Requires-Dist: numpy>=1.24
Requires-Dist: bitarray>=2.8
Provides-Extra: dev
Requires-Dist: pytest>=7.4; extra == "dev"
Requires-Dist: pytest-cov>=4.1; extra == "dev"
Requires-Dist: pytest-benchmark>=4.0; extra == "dev"
Requires-Dist: hypothesis>=6.100; extra == "dev"
Requires-Dist: black; extra == "dev"
Requires-Dist: ruff; extra == "dev"
Requires-Dist: isort; extra == "dev"
Requires-Dist: mypy; extra == "dev"
Requires-Dist: pre-commit; extra == "dev"
Dynamic: license-file
